myridek12_parent_api/__init__.py
myridek12_parent_api/base.py
myridek12_parent_api/myridek12.py
myridek12_parent_api/myridek12_api_client.py
myridek12_parent_api/errors/__init__.py
myridek12_parent_api/errors/myridek12_error.py
myridek12_parent_api/models/__init__.py
myridek12_parent_api/models/address.py
myridek12_parent_api/models/base.py
myridek12_parent_api/models/busrun.py
myridek12_parent_api/models/busrundetail.py
myridek12_parent_api/models/busstop.py
myridek12_parent_api/models/customfield.py
myridek12_parent_api/models/student.py
myridek12_parent_api-0.0.13.dist-info/METADATA
myridek12_parent_api-0.0.13.dist-info/WHEEL
myridek12_parent_api-0.0.13.dist-info/top_level.txt
myridek12_parent_api-0.0.13.dist-info/RECORD
